{".class": "MypyFile", "_fullname": "dmt.tk.journal.message", "is_partial_stub_package": false, "is_stub": false, "names": {".class": "SymbolTable", "ABC": {".class": "SymbolTableNode", "cross_ref": "abc.ABC", "kind": "Gdef"}, "Alert": {".class": "SymbolTableNode", "kind": "Gdef", "node": {".class": "TypeInfo", "_promote": null, "abstract_attributes": [], "bases": ["dmt.tk.journal.message.Message"], "declared_metaclass": null, "defn": {".class": "ClassDef", "fullname": "dmt.tk.journal.message.Alert", "name": "Alert", "type_vars": []}, "flags": [], "fullname": "dmt.tk.journal.message.Alert", "metaclass_type": "abc.ABCMeta", "metadata": {}, "module_name": "dmt.tk.journal.message", "mro": ["dmt.tk.journal.message.Alert", "dmt.tk.journal.message.Message", "abc.ABC", "builtins.object"], "names": {".class": "SymbolTable", "label": {".class": "SymbolTableNode", "kind": "Mdef", "node": {".class": "Var", "flags": ["is_initialized_in_class", "is_ready"], "fullname": "dmt.tk.journal.message.Alert.label", "name": "label", "type": "builtins.str"}}, "level": {".class": "SymbolTableNode", "kind": "Mdef", "node": {".class": "Var", "flags": ["is_initialized_in_class"], "fullname": "dmt.tk.journal.message.Alert.level", "name": "level", "type": "dmt.tk.journal.Level"}}}, "tuple_type": null, "type_vars": [], "typeddict_type": null}}, "Assertion": {".class": "SymbolTableNode", "kind": "Gdef", "node": {".class": "TypeInfo", "_promote": null, "abstract_attributes": [], "bases": ["dmt.tk.journal.message.Message"], "declared_metaclass": null, "defn": {".class": "ClassDef", "fullname": "dmt.tk.journal.message.Assertion", "name": "Assertion", "type_vars": []}, "flags": [], "fullname": "dmt.tk.journal.message.Assertion", "metaclass_type": "abc.ABCMeta", "metadata": {}, "module_name": "dmt.tk.journal.message", "mro": ["dmt.tk.journal.message.Assertion", "dmt.tk.journal.message.Message", "abc.ABC", "builtins.object"], "names": {".class": "SymbolTable", "label": {".class": "SymbolTableNode", "kind": "Mdef", "node": {".class": "Var", "flags": ["is_initialized_in_class", "is_ready"], "fullname": "dmt.tk.journal.message.Assertion.label", "name": "label", "type": "builtins.str"}}, "level": {".class": "SymbolTableNode", "kind": "Mdef", "node": {".class": "Var", "flags": ["is_initialized_in_class"], "fullname": "dmt.tk.journal.message.Assertion.level", "name": "level", "type": "dmt.tk.journal.Level"}}}, "tuple_type": null, "type_vars": [], "typeddict_type": null}}, "Attention": {".class": "SymbolTableNode", "kind": "Gdef", "node": {".class": "TypeInfo", "_promote": null, "abstract_attributes": [], "bases": ["dmt.tk.journal.message.Alert"], "declared_metaclass": null, "defn": {".class": "ClassDef", "fullname": "dmt.tk.journal.message.Attention", "name": "Attention", "type_vars": []}, "flags": [], "fullname": "dmt.tk.journal.message.Attention", "metaclass_type": "abc.ABCMeta", "metadata": {}, "module_name": "dmt.tk.journal.message", "mro": ["dmt.tk.journal.message.Attention", "dmt.tk.journal.message.Alert", "dmt.tk.journal.message.Message", "abc.ABC", "builtins.object"], "names": {".class": "SymbolTable", "label": {".class": "SymbolTableNode", "kind": "Mdef", "node": {".class": "Var", "flags": ["is_initialized_in_class", "is_ready"], "fullname": "dmt.tk.journal.message.Attention.label", "name": "label", "type": "builtins.str"}}}, "tuple_type": null, "type_vars": [], "typeddict_type": null}}, "ContextualMessage": {".class": "SymbolTableNode", "kind": "Gdef", "node": {".class": "TypeInfo", "_promote": null, "abstract_attributes": [], "bases": ["builtins.object"], "declared_metaclass": null, "defn": {".class": "ClassDef", "fullname": "dmt.tk.journal.message.ContextualMessage", "name": "ContextualMessage", "type_vars": []}, "flags": [], "fullname": "dmt.tk.journal.message.ContextualMessage", "metaclass_type": null, "metadata": {}, "module_name": "dmt.tk.journal.message", "mro": ["dmt.tk.journal.message.ContextualMessage", "builtins.object"], "names": {".class": "SymbolTable", "__init__": {".class": "SymbolTableNode", "kind": "Mdef", "node": {".class": "FuncDef", "arg_kinds": [0, 0, 0, 2, 4], "arg_names": ["self", "context", "message", "args", "kwargs"], "flags": [], "fullname": "dmt.tk.journal.message.ContextualMessage.__init__", "name": "__init__", "type": null}}, "_context": {".class": "SymbolTableNode", "implicit": true, "kind": "Mdef", "node": {".class": "Var", "flags": [], "fullname": "dmt.tk.journal.message.ContextualMessage._context", "name": "_context", "type": {".class": "AnyType", "missing_import_name": null, "source_any": null, "type_of_any": 1}}}, "_message": {".class": "SymbolTableNode", "implicit": true, "kind": "Mdef", "node": {".class": "Var", "flags": [], "fullname": "dmt.tk.journal.message.ContextualMessage._message", "name": "_message", "type": {".class": "AnyType", "missing_import_name": null, "source_any": null, "type_of_any": 1}}}, "context": {".class": "SymbolTableNode", "kind": "Mdef", "node": {".class": "Decorator", "func": {".class": "FuncDef", "arg_kinds": [0], "arg_names": ["self"], "flags": ["is_property", "is_decorated"], "fullname": "dmt.tk.journal.message.ContextualMessage.context", "name": "context", "type": null}, "is_overload": false, "var": {".class": "Var", "flags": ["is_initialized_in_class", "is_property", "is_ready"], "fullname": null, "name": "context", "type": {".class": "CallableType", "arg_kinds": [0], "arg_names": ["self"], "arg_types": ["dmt.tk.journal.message.ContextualMessage"], "bound_args": [], "def_extras": {}, "fallback": "builtins.function", "implicit": true, "is_ellipsis_args": false, "name": "context of ContextualMessage", "ret_type": {".class": "AnyType", "missing_import_name": null, "source_any": null, "type_of_any": 1}, "variables": []}}}}, "message": {".class": "SymbolTableNode", "kind": "Mdef", "node": {".class": "Decorator", "func": {".class": "FuncDef", "arg_kinds": [0], "arg_names": ["self"], "flags": ["is_property", "is_decorated"], "fullname": "dmt.tk.journal.message.ContextualMessage.message", "name": "message", "type": null}, "is_overload": false, "var": {".class": "Var", "flags": ["is_initialized_in_class", "is_property", "is_ready"], "fullname": null, "name": "message", "type": {".class": "CallableType", "arg_kinds": [0], "arg_names": ["self"], "arg_types": ["dmt.tk.journal.message.ContextualMessage"], "bound_args": [], "def_extras": {}, "fallback": "builtins.function", "implicit": true, "is_ellipsis_args": false, "name": "message of ContextualMessage", "ret_type": {".class": "AnyType", "missing_import_name": null, "source_any": null, "type_of_any": 1}, "variables": []}}}}}, "tuple_type": null, "type_vars": [], "typeddict_type": null}}, "DebugInfo": {".class": "SymbolTableNode", "kind": "Gdef", "node": {".class": "TypeInfo", "_promote": null, "abstract_attributes": [], "bases": ["dmt.tk.journal.message.Message"], "declared_metaclass": null, "defn": {".class": "ClassDef", "fullname": "dmt.tk.journal.message.DebugInfo", "name": "DebugInfo", "type_vars": []}, "flags": [], "fullname": "dmt.tk.journal.message.DebugInfo", "metaclass_type": "abc.ABCMeta", "metadata": {}, "module_name": "dmt.tk.journal.message", "mro": ["dmt.tk.journal.message.DebugInfo", "dmt.tk.journal.message.Message", "abc.ABC", "builtins.object"], "names": {".class": "SymbolTable", "label": {".class": "SymbolTableNode", "kind": "Mdef", "node": {".class": "Var", "flags": ["is_initialized_in_class", "is_ready"], "fullname": "dmt.tk.journal.message.DebugInfo.label", "name": "label", "type": "builtins.str"}}, "level": {".class": "SymbolTableNode", "kind": "Mdef", "node": {".class": "Var", "flags": ["is_initialized_in_class"], "fullname": "dmt.tk.journal.message.DebugInfo.level", "name": "level", "type": "dmt.tk.journal.Level"}}}, "tuple_type": null, "type_vars": [], "typeddict_type": null}}, "DevNote": {".class": "SymbolTableNode", "kind": "Gdef", "node": {".class": "TypeInfo", "_promote": null, "abstract_attributes": [], "bases": ["dmt.tk.journal.message.Note"], "declared_metaclass": null, "defn": {".class": "ClassDef", "fullname": "dmt.tk.journal.message.DevNote", "name": "DevNote", "type_vars": []}, "flags": [], "fullname": "dmt.tk.journal.message.DevNote", "metaclass_type": "abc.ABCMeta", "metadata": {}, "module_name": "dmt.tk.journal.message", "mro": ["dmt.tk.journal.message.DevNote", "dmt.tk.journal.message.Note", "dmt.tk.journal.message.Message", "abc.ABC", "builtins.object"], "names": {".class": "SymbolTable", "label": {".class": "SymbolTableNode", "kind": "Mdef", "node": {".class": "Var", "flags": ["is_initialized_in_class", "is_ready"], "fullname": "dmt.tk.journal.message.DevNote.label", "name": "label", "type": "builtins.str"}}}, "tuple_type": null, "type_vars": [], "typeddict_type": null}}, "Dialog": {".class": "SymbolTableNode", "kind": "Gdef", "node": {".class": "TypeInfo", "_promote": null, "abstract_attributes": [], "bases": ["dmt.tk.journal.message.Message"], "declared_metaclass": null, "defn": {".class": "ClassDef", "fullname": "dmt.tk.journal.message.Dialog", "name": "Dialog", "type_vars": []}, "flags": [], "fullname": "dmt.tk.journal.message.Dialog", "metaclass_type": "abc.ABCMeta", "metadata": {}, "module_name": "dmt.tk.journal.message", "mro": ["dmt.tk.journal.message.Dialog", "dmt.tk.journal.message.Message", "abc.ABC", "builtins.object"], "names": {".class": "SymbolTable", "label": {".class": "SymbolTableNode", "kind": "Mdef", "node": {".class": "Var", "flags": ["is_initialized_in_class", "is_ready"], "fullname": "dmt.tk.journal.message.Dialog.label", "name": "label", "type": "builtins.str"}}, "level": {".class": "SymbolTableNode", "kind": "Mdef", "node": {".class": "Var", "flags": ["is_initialized_in_class"], "fullname": "dmt.tk.journal.message.Dialog.level", "name": "level", "type": "dmt.tk.journal.Level"}}}, "tuple_type": null, "type_vars": [], "typeddict_type": null}}, "Error": {".class": "SymbolTableNode", "kind": "Gdef", "node": {".class": "TypeInfo", "_promote": null, "abstract_attributes": [], "bases": ["dmt.tk.journal.message.Message"], "declared_metaclass": null, "defn": {".class": "ClassDef", "fullname": "dmt.tk.journal.message.Error", "name": "Error", "type_vars": []}, "flags": [], "fullname": "dmt.tk.journal.message.Error", "metaclass_type": "abc.ABCMeta", "metadata": {}, "module_name": "dmt.tk.journal.message", "mro": ["dmt.tk.journal.message.Error", "dmt.tk.journal.message.Message", "abc.ABC", "builtins.object"], "names": {".class": "SymbolTable", "label": {".class": "SymbolTableNode", "kind": "Mdef", "node": {".class": "Var", "flags": ["is_initialized_in_class", "is_ready"], "fullname": "dmt.tk.journal.message.Error.label", "name": "label", "type": "builtins.str"}}, "level": {".class": "SymbolTableNode", "kind": "Mdef", "node": {".class": "Var", "flags": ["is_initialized_in_class"], "fullname": "dmt.tk.journal.message.Error.level", "name": "level", "type": "dmt.tk.journal.Level"}}}, "tuple_type": null, "type_vars": [], "typeddict_type": null}}, "Explanation": {".class": "SymbolTableNode", "kind": "Gdef", "node": {".class": "TypeInfo", "_promote": null, "abstract_attributes": [], "bases": ["dmt.tk.journal.message.Message"], "declared_metaclass": null, "defn": {".class": "ClassDef", "fullname": "dmt.tk.journal.message.Explanation", "name": "Explanation", "type_vars": []}, "flags": [], "fullname": "dmt.tk.journal.message.Explanation", "metaclass_type": "abc.ABCMeta", "metadata": {}, "module_name": "dmt.tk.journal.message", "mro": ["dmt.tk.journal.message.Explanation", "dmt.tk.journal.message.Message", "abc.ABC", "builtins.object"], "names": {".class": "SymbolTable", "label": {".class": "SymbolTableNode", "kind": "Mdef", "node": {".class": "Var", "flags": ["is_initialized_in_class", "is_ready"], "fullname": "dmt.tk.journal.message.Explanation.label", "name": "label", "type": "builtins.str"}}, "level": {".class": "SymbolTableNode", "kind": "Mdef", "node": {".class": "Var", "flags": ["is_initialized_in_class"], "fullname": "dmt.tk.journal.message.Explanation.level", "name": "level", "type": "dmt.tk.journal.Level"}}}, "tuple_type": null, "type_vars": [], "typeddict_type": null}}, "Failure": {".class": "SymbolTableNode", "kind": "Gdef", "node": {".class": "TypeInfo", "_promote": null, "abstract_attributes": [], "bases": ["dmt.tk.journal.message.Message"], "declared_metaclass": null, "defn": {".class": "ClassDef", "fullname": "dmt.tk.journal.message.Failure", "name": "Failure", "type_vars": []}, "flags": [], "fullname": "dmt.tk.journal.message.Failure", "metaclass_type": "abc.ABCMeta", "metadata": {}, "module_name": "dmt.tk.journal.message", "mro": ["dmt.tk.journal.message.Failure", "dmt.tk.journal.message.Message", "abc.ABC", "builtins.object"], "names": {".class": "SymbolTable", "label": {".class": "SymbolTableNode", "kind": "Mdef", "node": {".class": "Var", "flags": ["is_initialized_in_class", "is_ready"], "fullname": "dmt.tk.journal.message.Failure.label", "name": "label", "type": "builtins.str"}}, "level": {".class": "SymbolTableNode", "kind": "Mdef", "node": {".class": "Var", "flags": ["is_initialized_in_class"], "fullname": "dmt.tk.journal.message.Failure.level", "name": "level", "type": "dmt.tk.journal.Level"}}}, "tuple_type": null, "type_vars": [], "typeddict_type": null}}, "Funda": {".class": "SymbolTableNode", "kind": "Gdef", "node": {".class": "TypeInfo", "_promote": null, "abstract_attributes": [], "bases": ["dmt.tk.journal.message.Message"], "declared_metaclass": null, "defn": {".class": "ClassDef", "fullname": "dmt.tk.journal.message.Funda", "name": "Funda", "type_vars": []}, "flags": [], "fullname": "dmt.tk.journal.message.Funda", "metaclass_type": "abc.ABCMeta", "metadata": {}, "module_name": "dmt.tk.journal.message", "mro": ["dmt.tk.journal.message.Funda", "dmt.tk.journal.message.Message", "abc.ABC", "builtins.object"], "names": {".class": "SymbolTable", "label": {".class": "SymbolTableNode", "kind": "Mdef", "node": {".class": "Var", "flags": ["is_initialized_in_class", "is_ready"], "fullname": "dmt.tk.journal.message.Funda.label", "name": "label", "type": "builtins.str"}}, "level": {".class": "SymbolTableNode", "kind": "Mdef", "node": {".class": "Var", "flags": ["is_initialized_in_class"], "fullname": "dmt.tk.journal.message.Funda.level", "name": "level", "type": "dmt.tk.journal.Level"}}}, "tuple_type": null, "type_vars": [], "typeddict_type": null}}, "Info": {".class": "SymbolTableNode", "kind": "Gdef", "node": {".class": "TypeInfo", "_promote": null, "abstract_attributes": [], "bases": ["dmt.tk.journal.message.Message"], "declared_metaclass": null, "defn": {".class": "ClassDef", "fullname": "dmt.tk.journal.message.Info", "name": "Info", "type_vars": []}, "flags": [], "fullname": "dmt.tk.journal.message.Info", "metaclass_type": "abc.ABCMeta", "metadata": {}, "module_name": "dmt.tk.journal.message", "mro": ["dmt.tk.journal.message.Info", "dmt.tk.journal.message.Message", "abc.ABC", "builtins.object"], "names": {".class": "SymbolTable", "label": {".class": "SymbolTableNode", "kind": "Mdef", "node": {".class": "Var", "flags": ["is_initialized_in_class", "is_ready"], "fullname": "dmt.tk.journal.message.Info.label", "name": "label", "type": "builtins.str"}}, "level": {".class": "SymbolTableNode", "kind": "Mdef", "node": {".class": "Var", "flags": ["is_initialized_in_class"], "fullname": "dmt.tk.journal.message.Info.level", "name": "level", "type": "dmt.tk.journal.Level"}}}, "tuple_type": null, "type_vars": [], "typeddict_type": null}}, "Level": {".class": "SymbolTableNode", "cross_ref": "dmt.tk.journal.Level", "kind": "Gdef"}, "Message": {".class": "SymbolTableNode", "kind": "Gdef", "node": {".class": "TypeInfo", "_promote": null, "abstract_attributes": ["label", "level"], "bases": ["abc.ABC"], "declared_metaclass": null, "defn": {".class": "ClassDef", "fullname": "dmt.tk.journal.message.Message", "name": "Message", "type_vars": []}, "flags": ["is_abstract"], "fullname": "dmt.tk.journal.message.Message", "metaclass_type": "abc.ABCMeta", "metadata": {}, "module_name": "dmt.tk.journal.message", "mro": ["dmt.tk.journal.message.Message", "abc.ABC", "builtins.object"], "names": {".class": "SymbolTable", "__add__": {".class": "SymbolTableNode", "kind": "Mdef", "node": {".class": "FuncDef", "arg_kinds": [0, 0], "arg_names": ["self", "that"], "flags": [], "fullname": "dmt.tk.journal.message.Message.__add__", "name": "__add__", "type": null}}, "__init__": {".class": "SymbolTableNode", "kind": "Mdef", "node": {".class": "FuncDef", "arg_kinds": [0, 2, 5, 4], "arg_names": ["self", "msgs", "timestamp", "kwargs"], "flags": [], "fullname": "dmt.tk.journal.message.Message.__init__", "name": "__init__", "type": null}}, "_line_char": {".class": "SymbolTableNode", "implicit": true, "kind": "Mdef", "node": {".class": "Var", "flags": [], "fullname": "dmt.tk.journal.message.Message._line_char", "name": "_line_char", "type": {".class": "AnyType", "missing_import_name": null, "source_any": null, "type_of_any": 1}}}, "_line_length": {".class": "SymbolTableNode", "implicit": true, "kind": "Mdef", "node": {".class": "Var", "flags": [], "fullname": "dmt.tk.journal.message.Message._line_length", "name": "_line_length", "type": {".class": "AnyType", "missing_import_name": null, "source_any": null, "type_of_any": 1}}}, "_timestamp": {".class": "SymbolTableNode", "implicit": true, "kind": "Mdef", "node": {".class": "Var", "flags": [], "fullname": "dmt.tk.journal.message.Message._timestamp", "name": "_timestamp", "type": {".class": "AnyType", "missing_import_name": null, "source_any": null, "type_of_any": 1}}}, "_value": {".class": "SymbolTableNode", "implicit": true, "kind": "Mdef", "node": {".class": "Var", "flags": [], "fullname": "dmt.tk.journal.message.Message._value", "name": "_value", "type": {".class": "AnyType", "missing_import_name": null, "source_any": null, "type_of_any": 1}}}, "formatted": {".class": "SymbolTableNode", "kind": "Mdef", "node": {".class": "FuncDef", "arg_kinds": [0, 1], "arg_names": ["self", "caller"], "flags": [], "fullname": "dmt.tk.journal.message.Message.formatted", "name": "formatted", "type": null}}, "label": {".class": "SymbolTableNode", "kind": "Mdef", "node": {".class": "Decorator", "func": {".class": "FuncDef", "arg_kinds": [0], "arg_names": ["self"], "flags": ["is_property", "is_decorated", "is_abstract"], "fullname": "dmt.tk.journal.message.Message.label", "name": "label", "type": null}, "is_overload": false, "var": {".class": "Var", "flags": ["is_initialized_in_class", "is_property", "is_ready"], "fullname": null, "name": "label", "type": {".class": "CallableType", "arg_kinds": [0], "arg_names": ["self"], "arg_types": ["dmt.tk.journal.message.Message"], "bound_args": [], "def_extras": {}, "fallback": "builtins.function", "implicit": true, "is_ellipsis_args": false, "name": "label of Message", "ret_type": {".class": "AnyType", "missing_import_name": null, "source_any": null, "type_of_any": 1}, "variables": []}}}}, "labelstamp": {".class": "SymbolTableNode", "kind": "Mdef", "node": {".class": "Decorator", "func": {".class": "FuncDef", "arg_kinds": [0], "arg_names": ["self"], "flags": ["is_property", "is_decorated"], "fullname": "dmt.tk.journal.message.Message.labelstamp", "name": "labelstamp", "type": null}, "is_overload": false, "var": {".class": "Var", "flags": ["is_initialized_in_class", "is_property", "is_ready"], "fullname": null, "name": "labelstamp", "type": {".class": "CallableType", "arg_kinds": [0], "arg_names": ["self"], "arg_types": ["dmt.tk.journal.message.Message"], "bound_args": [], "def_extras": {}, "fallback": "builtins.function", "implicit": true, "is_ellipsis_args": false, "name": "labelstamp of Message", "ret_type": {".class": "AnyType", "missing_import_name": null, "source_any": null, "type_of_any": 1}, "variables": []}}}}, "level": {".class": "SymbolTableNode", "kind": "Mdef", "node": {".class": "Decorator", "func": {".class": "FuncDef", "arg_kinds": [0], "arg_names": ["self"], "flags": ["is_property", "is_decorated", "is_abstract"], "fullname": "dmt.tk.journal.message.Message.level", "name": "level", "type": null}, "is_overload": false, "var": {".class": "Var", "flags": ["is_initialized_in_class", "is_property", "is_ready"], "fullname": null, "name": "level", "type": {".class": "CallableType", "arg_kinds": [0], "arg_names": ["self"], "arg_types": ["dmt.tk.journal.message.Message"], "bound_args": [], "def_extras": {}, "fallback": "builtins.function", "implicit": true, "is_ellipsis_args": false, "name": "level of Message", "ret_type": {".class": "AnyType", "missing_import_name": null, "source_any": null, "type_of_any": 1}, "variables": []}}}}, "timestamp": {".class": "SymbolTableNode", "kind": "Mdef", "node": {".class": "Decorator", "func": {".class": "FuncDef", "arg_kinds": [0], "arg_names": ["self"], "flags": ["is_property", "is_decorated"], "fullname": "dmt.tk.journal.message.Message.timestamp", "name": "timestamp", "type": null}, "is_overload": false, "var": {".class": "Var", "flags": ["is_initialized_in_class", "is_property", "is_ready"], "fullname": null, "name": "timestamp", "type": {".class": "CallableType", "arg_kinds": [0], "arg_names": ["self"], "arg_types": ["dmt.tk.journal.message.Message"], "bound_args": [], "def_extras": {}, "fallback": "builtins.function", "implicit": true, "is_ellipsis_args": false, "name": "timestamp of Message", "ret_type": {".class": "AnyType", "missing_import_name": null, "source_any": null, "type_of_any": 1}, "variables": []}}}}, "value": {".class": "SymbolTableNode", "kind": "Mdef", "node": {".class": "Decorator", "func": {".class": "FuncDef", "arg_kinds": [0], "arg_names": ["self"], "flags": ["is_property", "is_decorated"], "fullname": "dmt.tk.journal.message.Message.value", "name": "value", "type": null}, "is_overload": false, "var": {".class": "Var", "flags": ["is_initialized_in_class", "is_property", "is_ready"], "fullname": null, "name": "value", "type": {".class": "CallableType", "arg_kinds": [0], "arg_names": ["self"], "arg_types": ["dmt.tk.journal.message.Message"], "bound_args": [], "def_extras": {}, "fallback": "builtins.function", "implicit": true, "is_ellipsis_args": false, "name": "value of Message", "ret_type": {".class": "AnyType", "missing_import_name": null, "source_any": null, "type_of_any": 1}, "variables": []}}}}}, "tuple_type": null, "type_vars": [], "typeddict_type": null}}, "Note": {".class": "SymbolTableNode", "kind": "Gdef", "node": {".class": "TypeInfo", "_promote": null, "abstract_attributes": [], "bases": ["dmt.tk.journal.message.Message"], "declared_metaclass": null, "defn": {".class": "ClassDef", "fullname": "dmt.tk.journal.message.Note", "name": "Note", "type_vars": []}, "flags": [], "fullname": "dmt.tk.journal.message.Note", "metaclass_type": "abc.ABCMeta", "metadata": {}, "module_name": "dmt.tk.journal.message", "mro": ["dmt.tk.journal.message.Note", "dmt.tk.journal.message.Message", "abc.ABC", "builtins.object"], "names": {".class": "SymbolTable", "label": {".class": "SymbolTableNode", "kind": "Mdef", "node": {".class": "Var", "flags": ["is_initialized_in_class", "is_ready"], "fullname": "dmt.tk.journal.message.Note.label", "name": "label", "type": "builtins.str"}}, "level": {".class": "SymbolTableNode", "kind": "Mdef", "node": {".class": "Var", "flags": ["is_initialized_in_class"], "fullname": "dmt.tk.journal.message.Note.level", "name": "level", "type": "dmt.tk.journal.Level"}}}, "tuple_type": null, "type_vars": [], "typeddict_type": null}}, "Notice": {".class": "SymbolTableNode", "kind": "Gdef", "node": {".class": "TypeInfo", "_promote": null, "abstract_attributes": [], "bases": ["dmt.tk.journal.message.Alert"], "declared_metaclass": null, "defn": {".class": "ClassDef", "fullname": "dmt.tk.journal.message.Notice", "name": "Notice", "type_vars": []}, "flags": [], "fullname": "dmt.tk.journal.message.Notice", "metaclass_type": "abc.ABCMeta", "metadata": {}, "module_name": "dmt.tk.journal.message", "mro": ["dmt.tk.journal.message.Notice", "dmt.tk.journal.message.Alert", "dmt.tk.journal.message.Message", "abc.ABC", "builtins.object"], "names": {".class": "SymbolTable", "label": {".class": "SymbolTableNode", "kind": "Mdef", "node": {".class": "Var", "flags": ["is_initialized_in_class", "is_ready"], "fullname": "dmt.tk.journal.message.Notice.label", "name": "label", "type": "builtins.str"}}}, "tuple_type": null, "type_vars": [], "typeddict_type": null}}, "ProgressInfo": {".class": "SymbolTableNode", "kind": "Gdef", "node": {".class": "TypeInfo", "_promote": null, "abstract_attributes": [], "bases": ["dmt.tk.journal.message.Info"], "declared_metaclass": null, "defn": {".class": "ClassDef", "fullname": "dmt.tk.journal.message.ProgressInfo", "name": "ProgressInfo", "type_vars": []}, "flags": [], "fullname": "dmt.tk.journal.message.ProgressInfo", "metaclass_type": "abc.ABCMeta", "metadata": {}, "module_name": "dmt.tk.journal.message", "mro": ["dmt.tk.journal.message.ProgressInfo", "dmt.tk.journal.message.Info", "dmt.tk.journal.message.Message", "abc.ABC", "builtins.object"], "names": {".class": "SymbolTable", "label": {".class": "SymbolTableNode", "kind": "Mdef", "node": {".class": "Var", "flags": ["is_initialized_in_class", "is_ready"], "fullname": "dmt.tk.journal.message.ProgressInfo.label", "name": "label", "type": "builtins.str"}}}, "tuple_type": null, "type_vars": [], "typeddict_type": null}}, "Remark": {".class": "SymbolTableNode", "kind": "Gdef", "node": {".class": "TypeInfo", "_promote": null, "abstract_attributes": [], "bases": ["dmt.tk.journal.message.Info"], "declared_metaclass": null, "defn": {".class": "ClassDef", "fullname": "dmt.tk.journal.message.Remark", "name": "Remark", "type_vars": []}, "flags": [], "fullname": "dmt.tk.journal.message.Remark", "metaclass_type": "abc.ABCMeta", "metadata": {}, "module_name": "dmt.tk.journal.message", "mro": ["dmt.tk.journal.message.Remark", "dmt.tk.journal.message.Info", "dmt.tk.journal.message.Message", "abc.ABC", "builtins.object"], "names": {".class": "SymbolTable", "label": {".class": "SymbolTableNode", "kind": "Mdef", "node": {".class": "Var", "flags": ["is_initialized_in_class", "is_ready"], "fullname": "dmt.tk.journal.message.Remark.label", "name": "label", "type": "builtins.str"}}}, "tuple_type": null, "type_vars": [], "typeddict_type": null}}, "SourceCodeInfo": {".class": "SymbolTableNode", "kind": "Gdef", "node": {".class": "TypeInfo", "_promote": null, "abstract_attributes": [], "bases": ["dmt.tk.journal.message.Message"], "declared_metaclass": null, "defn": {".class": "ClassDef", "fullname": "dmt.tk.journal.message.SourceCodeInfo", "name": "SourceCodeInfo", "type_vars": []}, "flags": [], "fullname": "dmt.tk.journal.message.SourceCodeInfo", "metaclass_type": "abc.ABCMeta", "metadata": {}, "module_name": "dmt.tk.journal.message", "mro": ["dmt.tk.journal.message.SourceCodeInfo", "dmt.tk.journal.message.Message", "abc.ABC", "builtins.object"], "names": {".class": "SymbolTable", "__init__": {".class": "SymbolTableNode", "kind": "Mdef", "node": {".class": "FuncDef", "arg_kinds": [0, 1, 2, 4], "arg_names": ["self", "level", "msgs", "kwargs"], "flags": [], "fullname": "dmt.tk.journal.message.SourceCodeInfo.__init__", "name": "__init__", "type": null}}, "_level": {".class": "SymbolTableNode", "implicit": true, "kind": "Mdef", "node": {".class": "Var", "flags": [], "fullname": "dmt.tk.journal.message.SourceCodeInfo._level", "name": "_level", "type": {".class": "AnyType", "missing_import_name": null, "source_any": null, "type_of_any": 1}}}, "label": {".class": "SymbolTableNode", "kind": "Mdef", "node": {".class": "Var", "flags": ["is_initialized_in_class", "is_ready"], "fullname": "dmt.tk.journal.message.SourceCodeInfo.label", "name": "label", "type": "builtins.str"}}, "level": {".class": "SymbolTableNode", "kind": "Mdef", "node": {".class": "Decorator", "func": {".class": "FuncDef", "arg_kinds": [0], "arg_names": ["self"], "flags": ["is_property", "is_decorated"], "fullname": "dmt.tk.journal.message.SourceCodeInfo.level", "name": "level", "type": null}, "is_overload": false, "var": {".class": "Var", "flags": ["is_initialized_in_class", "is_property", "is_ready"], "fullname": null, "name": "level", "type": {".class": "CallableType", "arg_kinds": [0], "arg_names": ["self"], "arg_types": ["dmt.tk.journal.message.SourceCodeInfo"], "bound_args": [], "def_extras": {}, "fallback": "builtins.function", "implicit": true, "is_ellipsis_args": false, "name": "level of SourceCodeInfo", "ret_type": {".class": "AnyType", "missing_import_name": null, "source_any": null, "type_of_any": 1}, "variables": []}}}}}, "tuple_type": null, "type_vars": [], "typeddict_type": null}}, "Status": {".class": "SymbolTableNode", "kind": "Gdef", "node": {".class": "TypeInfo", "_promote": null, "abstract_attributes": [], "bases": ["dmt.tk.journal.message.Message"], "declared_metaclass": null, "defn": {".class": "ClassDef", "fullname": "dmt.tk.journal.message.Status", "name": "Status", "type_vars": []}, "flags": [], "fullname": "dmt.tk.journal.message.Status", "metaclass_type": "abc.ABCMeta", "metadata": {}, "module_name": "dmt.tk.journal.message", "mro": ["dmt.tk.journal.message.Status", "dmt.tk.journal.message.Message", "abc.ABC", "builtins.object"], "names": {".class": "SymbolTable", "label": {".class": "SymbolTableNode", "kind": "Mdef", "node": {".class": "Var", "flags": ["is_initialized_in_class", "is_ready"], "fullname": "dmt.tk.journal.message.Status.label", "name": "label", "type": "builtins.str"}}, "level": {".class": "SymbolTableNode", "kind": "Mdef", "node": {".class": "Var", "flags": ["is_initialized_in_class"], "fullname": "dmt.tk.journal.message.Status.level", "name": "level", "type": "dmt.tk.journal.Level"}}}, "tuple_type": null, "type_vars": [], "typeddict_type": null}}, "Success": {".class": "SymbolTableNode", "kind": "Gdef", "node": {".class": "TypeInfo", "_promote": null, "abstract_attributes": [], "bases": ["dmt.tk.journal.message.Message"], "declared_metaclass": null, "defn": {".class": "ClassDef", "fullname": "dmt.tk.journal.message.Success", "name": "Success", "type_vars": []}, "flags": [], "fullname": "dmt.tk.journal.message.Success", "metaclass_type": "abc.ABCMeta", "metadata": {}, "module_name": "dmt.tk.journal.message", "mro": ["dmt.tk.journal.message.Success", "dmt.tk.journal.message.Message", "abc.ABC", "builtins.object"], "names": {".class": "SymbolTable", "label": {".class": "SymbolTableNode", "kind": "Mdef", "node": {".class": "Var", "flags": ["is_initialized_in_class", "is_ready"], "fullname": "dmt.tk.journal.message.Success.label", "name": "label", "type": "builtins.str"}}, "level": {".class": "SymbolTableNode", "kind": "Mdef", "node": {".class": "Var", "flags": ["is_initialized_in_class"], "fullname": "dmt.tk.journal.message.Success.level", "name": "level", "type": "dmt.tk.journal.Level"}}}, "tuple_type": null, "type_vars": [], "typeddict_type": null}}, "Suggestion": {".class": "SymbolTableNode", "kind": "Gdef", "node": {".class": "TypeInfo", "_promote": null, "abstract_attributes": [], "bases": ["dmt.tk.journal.message.Message"], "declared_metaclass": null, "defn": {".class": "ClassDef", "fullname": "dmt.tk.journal.message.Suggestion", "name": "Suggestion", "type_vars": []}, "flags": [], "fullname": "dmt.tk.journal.message.Suggestion", "metaclass_type": "abc.ABCMeta", "metadata": {}, "module_name": "dmt.tk.journal.message", "mro": ["dmt.tk.journal.message.Suggestion", "dmt.tk.journal.message.Message", "abc.ABC", "builtins.object"], "names": {".class": "SymbolTable", "label": {".class": "SymbolTableNode", "kind": "Mdef", "node": {".class": "Var", "flags": ["is_initialized_in_class", "is_ready"], "fullname": "dmt.tk.journal.message.Suggestion.label", "name": "label", "type": "builtins.str"}}, "level": {".class": "SymbolTableNode", "kind": "Mdef", "node": {".class": "Var", "flags": ["is_initialized_in_class"], "fullname": "dmt.tk.journal.message.Suggestion.level", "name": "level", "type": "dmt.tk.journal.Level"}}}, "tuple_type": null, "type_vars": [], "typeddict_type": null}}, "Test": {".class": "SymbolTableNode", "kind": "Gdef", "node": {".class": "TypeInfo", "_promote": null, "abstract_attributes": [], "bases": ["dmt.tk.journal.message.Message"], "declared_metaclass": null, "defn": {".class": "ClassDef", "fullname": "dmt.tk.journal.message.Test", "name": "Test", "type_vars": []}, "flags": [], "fullname": "dmt.tk.journal.message.Test", "metaclass_type": "abc.ABCMeta", "metadata": {}, "module_name": "dmt.tk.journal.message", "mro": ["dmt.tk.journal.message.Test", "dmt.tk.journal.message.Message", "abc.ABC", "builtins.object"], "names": {".class": "SymbolTable", "label": {".class": "SymbolTableNode", "kind": "Mdef", "node": {".class": "Var", "flags": ["is_initialized_in_class", "is_ready"], "fullname": "dmt.tk.journal.message.Test.label", "name": "label", "type": "builtins.str"}}, "level": {".class": "SymbolTableNode", "kind": "Mdef", "node": {".class": "Var", "flags": ["is_initialized_in_class"], "fullname": "dmt.tk.journal.message.Test.level", "name": "level", "type": "dmt.tk.journal.Level"}}}, "tuple_type": null, "type_vars": [], "typeddict_type": null}}, "__doc__": {".class": "SymbolTableNode", "kind": "Gdef", "node": {".class": "Var", "flags": ["is_ready"], "fullname": "dmt.tk.journal.message.__doc__", "name": "__doc__", "type": "builtins.str"}}, "__file__": {".class": "SymbolTableNode", "kind": "Gdef", "node": {".class": "Var", "flags": ["is_ready"], "fullname": "dmt.tk.journal.message.__file__", "name": "__file__", "type": "builtins.str"}}, "__name__": {".class": "SymbolTableNode", "kind": "Gdef", "node": {".class": "Var", "flags": ["is_ready"], "fullname": "dmt.tk.journal.message.__name__", "name": "__name__", "type": "builtins.str"}}, "__package__": {".class": "SymbolTableNode", "kind": "Gdef", "node": {".class": "Var", "flags": ["is_ready"], "fullname": "dmt.tk.journal.message.__package__", "name": "__package__", "type": "builtins.str"}}, "abstractmethod": {".class": "SymbolTableNode", "cross_ref": "abc.abstractmethod", "kind": "Gdef"}, "copy": {".class": "SymbolTableNode", "cross_ref": "copy", "kind": "Gdef"}, "time": {".class": "SymbolTableNode", "cross_ref": "time", "kind": "Gdef"}, "utils": {".class": "SymbolTableNode", "cross_ref": "dmt.tk.journal.utils", "kind": "Gdef"}}, "path": "/Users/vishalsoodmuchu/work/bbp/work/validations/dmt/dmt/tk/journal/message.py"}